pychatbots/__init__.py
pychatbots/compare.cp38-win_amd64.pyd
pychatbots/compare.py
pychatbots/module.cp38-win_amd64.pyd
pychatbots/module.py
pychatbots-1.1.4.dist-info/LICENSE
pychatbots-1.1.4.dist-info/METADATA
pychatbots-1.1.4.dist-info/WHEEL
pychatbots-1.1.4.dist-info/top_level.txt
pychatbots-1.1.4.dist-info/RECORD
