Metadata-Version: 2.1
Name: pychatbots
Version: 1.1.4
Summary: a good chatbot
Home-page: https://github.com/Zhou-chengy/pychatbot
Author: Zhou_Chengyu
Author-email: earuil@outlook.com
License: UNKNOWN
Platform: UNKNOWN
Requires-Python: ==3.8.*
